xodex/__init__.py
xodex/__main__.py
xodex/conf/__init__.py
xodex/conf/locale/en.json
xodex/conf/template/LICENSE
xodex/conf/template/README.md
xodex/conf/template/manage.py
xodex/conf/template/project/__init__.py
xodex/conf/template/project/__main__.py
xodex/conf/template/project/objects/__init__.py
xodex/conf/template/project/scenes/__init__.py
xodex/conf/template/project/settings.py
xodex/conf/template/requirements.txt
xodex/contrib/__init__.py
xodex/contrib/basicobjects.py
xodex/contrib/mainscene.py
xodex/core/__init__.py
xodex/core/exceptions.py
xodex/core/localization.py
xodex/core/management/__init__.py
xodex/core/management/command.py
xodex/core/management/commands/start.py
xodex/core/singleton.py
xodex/game/__init__.py
xodex/game/sounds.py
xodex/game/storage.py
xodex/objects/__init__.py
xodex/objects/animator.py
xodex/objects/image.py
xodex/objects/manager.py
xodex/objects/objects.py
xodex/objects/spritesheet.py
xodex/scenes/__init__.py
xodex/scenes/base_scene.py
xodex/scenes/blur_scene.py
xodex/scenes/manager.py
xodex/utils/__init__.py
xodex/utils/functions.py
xodex/utils/inputs.py
xodex/utils/log.py
xodex/utils/storage.py
xodex/utils/values.py
xodex/version.py
xodex-0.1.0.dist-info/licenses/LICENSE
xodex-0.1.0.dist-info/WHEEL
xodex-0.1.0.dist-info/entry_points.txt
xodex-0.1.0.dist-info/METADATA
xodex-0.1.0.dist-info/RECORD
