Metadata-Version: 2.4
Name: xodex
Version: 0.1.0
Summary: A modular, extensible Pygame game engine for rapid 2D game development.
Keywords: pygame,game engine,2d,xodex,games,engine,framework
Author: Sackey Ezekiel Etrue, Xodex Contributers
Author-email: Sackey Ezekiel Etrue <sackeyetrue@gmail.com>
License-Expression: MIT
License-File: LICENSE
Classifier: Intended Audience :: Developers
Classifier: License :: OSI Approved :: MIT License
Classifier: Programming Language :: Python :: 3
Classifier: Programming Language :: Python :: 3.9
Classifier: Programming Language :: Python :: 3.10
Classifier: Programming Language :: Python :: 3.11
Classifier: Programming Language :: Python :: 3.12
Classifier: Topic :: Games/Entertainment
Classifier: Topic :: Multimedia :: Graphics
Classifier: Topic :: Software Development :: Libraries :: Application Frameworks
Classifier: Operating System :: Microsoft :: Windows
Requires-Dist: pillow>=11.3.0
Requires-Dist: pygame>=2.6.1
Requires-Dist: pygameui
Requires-Dist: pytest ; extra == 'dev'
Maintainer: Sackey Ezekiel Etrue
Maintainer-email: Sackey Ezekiel Etrue <sackeyetrue@gmail.com>
Requires-Python: >=3.13
Project-URL: Documentation, https://github.com/djoezeke/xodex#readme
Project-URL: Homepage, https://github.com/djoezeke/xodex
Project-URL: Issues, https://github.com/djoezeke/xodex/issues
Project-URL: Release Notes, https://github.com/djoezeke/xodex/releases
Project-URL: Source, https://github.com/djoezeke/xodex
Provides-Extra: dev
Provides-Extra: docs
